Metadata-Version: 2.1
Name: rydeen-lesson-notebook-bad-code
Version: 0.1.3
Summary: Записная книжка (терминал). Bad code.
Home-page: https://www.python.org/sigs/distutils-sig/
Author: Dmitry Kozlovsky
Author-email: rem.dk83@gmail.com
